house_prices_regression_model/VERSION
house_prices_regression_model/__init__.py
house_prices_regression_model/pipeline.py
house_prices_regression_model/predict.py
house_prices_regression_model/train_pipeline.py
house_prices_regression_model/config/__init__.py
house_prices_regression_model/config/core.py
house_prices_regression_model/config/settings.yml
house_prices_regression_model/dat/__init__.py
house_prices_regression_model/dat/test.csv
house_prices_regression_model/dat/train.csv
house_prices_regression_model/processing/__init__.py
house_prices_regression_model/processing/data_manager.py
house_prices_regression_model/processing/data_validation.py
house_prices_regression_model/processing/pipeline_steps.py
house_prices_regression_model/trained_models/__init__.py
house_prices_regression_model/trained_models/house_prices_regression_model_v1.0.6.pkl
house_prices_regression_model-1.0.6.dist-info/LICENSE
house_prices_regression_model-1.0.6.dist-info/METADATA
house_prices_regression_model-1.0.6.dist-info/WHEEL
house_prices_regression_model-1.0.6.dist-info/top_level.txt
house_prices_regression_model-1.0.6.dist-info/RECORD
