Metadata-Version: 2.1
Name: house-prices-regression-model
Version: 1.0.6
Summary: Example regression model package from Train In Data.
Home-page: https://github.com/trainindata/testing-and-monitoring-ml-deployments
Author: Javier Monsalve Rodilla
Author-email: javiermonsalverodilla@gmail.com
License: BSD-3
Platform: UNKNOWN
Classifier: License :: OSI Approved :: MIT License
Classifier: Programming Language :: Python
Classifier: Programming Language :: Python :: 3
Classifier: Programming Language :: Python :: 3.6
Classifier: Programming Language :: Python :: 3.7
Classifier: Programming Language :: Python :: 3.8
Classifier: Programming Language :: Python :: 3.9
Classifier: Programming Language :: Python :: Implementation :: CPython
Classifier: Programming Language :: Python :: Implementation :: PyPy
Requires-Python: >=3.6.0
Requires-Dist: PyYAML (==5.4.1)
Requires-Dist: catboost (==0.26)
Requires-Dist: feature-engine (==1.1.2)
Requires-Dist: joblib (==0.15.1)
Requires-Dist: numpy (==1.19.0)
Requires-Dist: pandas (==1.2.1)
Requires-Dist: scikit-learn (==0.23.1)
